pytorm/__init__.py
pytorm/repository/__init__.py
pytorm/repository/abstract.py
pytorm/repository/abstract.pyi
pytorm/repository/repository.py
pytorm/repository/repository.pyi
pytorm-0.0.4.dist-info/LICENSE
pytorm-0.0.4.dist-info/WHEEL
pytorm-0.0.4.dist-info/METADATA
pytorm-0.0.4.dist-info/RECORD
